backgroundchanger/__init__.py
backgroundchanger/__main__.py
backgroundchanger/api.py
backgroundchanger/config.py
backgroundchanger/files.py
backgroundchanger/utils.py
tests/__init__.py
tests/conftest.py
tests/test_files.py
tests/test_utils.py
backgroundchanger-1.5.0.dist-info/LICENSE
backgroundchanger-1.5.0.dist-info/METADATA
backgroundchanger-1.5.0.dist-info/WHEEL
backgroundchanger-1.5.0.dist-info/entry_points.txt
backgroundchanger-1.5.0.dist-info/top_level.txt
backgroundchanger-1.5.0.dist-info/RECORD
