Metadata-Version: 2.1
Name: backgroundchanger
Version: 1.5.0
Summary: background changer using unsplash API.
Home-page: https://github.com/rugglcon/python-backgroundchanger
Author: Connor Ruggles
Author-email: conruggles@gmail.com
License: MIT
Platform: UNKNOWN
Classifier: Programming Language :: Python :: 3
Classifier: License :: OSI Approved :: MIT License
Requires-Python: >=3.5
Requires-Dist: requests (<3.0,>=2.0)
Requires-Dist: pywal (<4.0,>=3.0)
Requires-Dist: distro (<2.0,>=1.0)
